financefeast/__init__.py
financefeast/client.py
financefeast/common.py
financefeast/entity.py
financefeast/exceptions.py
financefeast/rest.py
financefeast/stream.py
financefeast-0.0.31.dist-info/LICENSE
financefeast-0.0.31.dist-info/METADATA
financefeast-0.0.31.dist-info/WHEEL
financefeast-0.0.31.dist-info/top_level.txt
financefeast-0.0.31.dist-info/RECORD
