Metadata-Version: 2.1
Name: financefeast
Version: 0.0.31
Summary: A client library for Financefeast API
Home-page: https://github.com/financefeast/python_client
Author: Financefeast
Author-email: support@financefeast.io
License: MIT
Platform: UNKNOWN
Classifier: Programming Language :: Python :: 3
Classifier: License :: OSI Approved :: MIT License
Classifier: Operating System :: OS Independent
Requires-Python: >=3.6
License-File: LICENSE
Requires-Dist: requests
Requires-Dist: websocket-client
